little_data_preprocessor/__init__.py
little_data_preprocessor/data_processsing_package.py
little_data_preprocessor-1.0.4.dist-info/METADATA
little_data_preprocessor-1.0.4.dist-info/WHEEL
little_data_preprocessor-1.0.4.dist-info/top_level.txt
little_data_preprocessor-1.0.4.dist-info/RECORD
