Metadata-Version: 2.1
Name: little_data_preprocessor
Version: 1.0.4
Summary: A pandas dataframe preprocessing python package
Home-page: https://github.com/Uncle-Solomon/little_preprocessor
Author: Ameh Solomon Onyeke
Author-email: amehsolomon46@gmail.com
Project-URL: Bug Tracker, https://github.com/Uncle-Solomon/little_preprocessor/issues
Project-URL: Documentation, https://github.com/Uncle-Solomon/little_preprocessor/wiki
Project-URL: Source Code, https://github.com/Uncle-Solomon/little_preprocessor
Keywords: python,pandas,preprocessing
Classifier: Development Status :: 3 - Alpha
Classifier: Intended Audience :: Education
Classifier: Programming Language :: Python :: 2
Classifier: Programming Language :: Python :: 3
Classifier: Operating System :: MacOS :: MacOS X
Classifier: Operating System :: Microsoft :: Windows
Requires-Dist: pandas
Requires-Dist: numpy
